django_powcaptcha/__init__.py
django_powcaptcha/apps.py
django_powcaptcha/client.py
django_powcaptcha/fields.py
django_powcaptcha/forms.py
django_powcaptcha/widgets.py
django_powcaptcha/templates/django_powcaptcha/widget.html
django_powcaptcha-0.0.3.dist-info/LICENSE
django_powcaptcha-0.0.3.dist-info/METADATA
django_powcaptcha-0.0.3.dist-info/WHEEL
django_powcaptcha-0.0.3.dist-info/top_level.txt
django_powcaptcha-0.0.3.dist-info/RECORD
