Metadata-Version: 2.1
Name: django-powcaptcha
Version: 0.0.3
Summary: Django PowCaptcha form field/widget app.
Home-page: https://github.com/aeyoll/django-powcaptcha
Author: Jean-Philippe Bidegain
Author-email: jp@bidega.in
License: BSD
Project-URL: Changelog, https://github.com/aeyoll/django-powcaptcha/blob/main/CHANGELOG.md
Project-URL: Issue Tracker, https://github.com/aeyoll/django-powcaptcha/issues
Keywords: django,powcaptcha
Classifier: Development Status :: 5 - Production/Stable
Classifier: Framework :: Django
Classifier: Framework :: Django :: 3.2
Classifier: Framework :: Django :: 4.1
Classifier: Framework :: Django :: 4.2
Classifier: Intended Audience :: Developers
Classifier: License :: OSI Approved :: BSD License
Classifier: Operating System :: OS Independent
Classifier: Programming Language :: Python
Classifier: Topic :: Internet :: WWW/HTTP :: Dynamic Content
Classifier: Programming Language :: Python :: 3
Classifier: Programming Language :: Python :: 3.9
Classifier: Programming Language :: Python :: 3.10
Classifier: Programming Language :: Python :: 3.11
License-File: LICENSE
Requires-Dist: django
